diarrhouea.py
diarrhouea-9999.0.0.dist-info/LICENSE.0BSD
diarrhouea-9999.0.0.dist-info/LICENSE.md
diarrhouea-9999.0.0.dist-info/METADATA
diarrhouea-9999.0.0.dist-info/WHEEL
diarrhouea-9999.0.0.dist-info/entry_points.txt
diarrhouea-9999.0.0.dist-info/top_level.txt
diarrhouea-9999.0.0.dist-info/RECORD
