Metadata-Version: 2.1
Name: diarrhouea
Version: 9999.0.0
Summary: Simple terminal emulator
Home-page: https://gitlab.com/0x46d59b71/diarrhouea
Author: Kirby Kevinson (0x46d59b71)
Author-email: 0x46d59b71@protonmail.com
License: BSD Zero Clause License
Keywords: terminal emulator
Platform: UNKNOWN
Classifier: Development Status :: 5 - Production/Stable
Classifier: Environment :: X11 Applications :: GTK
Classifier: License :: OSI Approved
Classifier: Operating System :: POSIX
Classifier: Programming Language :: Python :: 3
Classifier: Topic :: Terminals :: Terminal Emulators/X Terminals
